[
    {
      "id": 1,
      "name": "Basketball",
      "category": "Sports Goods",
      "sports": "Basketball",
      "sizes": ["Standard"],
      "thumbnail_url": "https://target.scene7.com/is/image/Target/GUEST_2233cc13-4d18-4d4a-988d-46c530676e1e?wid=600&hei=600&qlt=80&fmt=webp",
      "image_gallery": ["basketball1_1.jpg", "basketball1_2.jpg", "basketball1_3.jpg"],
      "rating": 4.5,
      "price": 29.99,
      "description": "Professional-grade basketball made from durable materials for indoor and outdoor play."
    },
    {
      "id": 2,
      "name": "Soccer Ball",
      "category": "Sports Goods",
      "sports": "Soccer",
      "sizes": ["Standard", "Junior"],
      "thumbnail_url": "https://target.scene7.com/is/image/Target/GUEST_1a073ce7-335f-47a5-b858-c2f50a4bc008?wid=600&hei=600&qlt=80&fmt=webp",
      "image_gallery": ["soccerball1_1.jpg", "soccerball1_2.jpg", "soccerball1_3.jpg"],
      "rating": 4.7,
      "price": 24.99,
      "description": "High-quality soccer ball designed for optimal performance and control on the field."
    },
    {
      "id": 3,
      "name": "Tennis Racket",
      "category": "Sports Gears",
      "sports": "Tennis",
      "sizes": ["27 inches", "25 inches"],
      "thumbnail_url": "https://target.scene7.com/is/image/Target/GUEST_a9307de1-8b92-4b68-a2c3-1affc025b94d?wid=600&hei=600&qlt=80&fmt=webp",
      "image_gallery": ["tennisracket1_1.jpg", "tennisracket1_2.jpg", "tennisracket1_3.jpg"],
      "rating": 4.8,
      "price": 89.99,
      "description": "Lightweight tennis racket with a large sweet spot for powerful and precise shots."
    },
    {
      "id": 4,
      "name": "Baseball Glove",
      "category": "Sports Gears",
      "sports": "Baseball",
      "sizes": ["Small", "Medium", "Large"],
      "thumbnail_url": "https://target.scene7.com/is/image/Target/GUEST_12010293-4eda-4a05-a841-44c20d8ed97c?wid=600&hei=600&qlt=80&fmt=webp",
      "image_gallery": ["baseballglove1_1.jpg", "baseballglove1_2.jpg", "baseballglove1_3.jpg"],
      "rating": 4.6,
      "price": 59.99,
      "description": "Premium leather baseball glove offering superior grip and comfort for players."
    },
    {
      "id": 5,
      "name": "Yoga Mat",
      "category": "Sports Goods",
      "sports": "Yoga",
      "sizes": ["Standard", "Extra Long"],
      "thumbnail_url": "https://target.scene7.com/is/image/Target/GUEST_5c940cda-0020-4707-ab38-b6858495e536?wid=600&hei=600&qlt=80&fmt=webp",
      "image_gallery": ["yogamat1_1.jpg", "yogamat1_2.jpg", "yogamat1_3.jpg"],
      "rating": 4.9,
      "price": 34.99,
      "description": "Eco-friendly yoga mat with non-slip surface, ideal for yoga and other fitness routines."
    },
    {
      "id": 6,
      "name": "Boxing Gloves",
      "category": "Sports Gears",
      "sports": "Boxing",
      "sizes": ["Small", "Medium", "Large"],
      "thumbnail_url": "https://target.scene7.com/is/image/Target/GUEST_45d9beeb-735f-4160-be52-724133695bdf?wid=600&hei=600&qlt=80&fmt=webp",
      "image_gallery": ["boxinggloves1_1.jpg", "boxinggloves1_2.jpg", "boxinggloves1_3.jpg"],
      "rating": 4.5,
      "price": 49.99,
      "description": "Durable boxing gloves with extra padding to protect your hands during intense training."
    },
    {
      "id": 7,
      "name": "Cricket Bat",
      "category": "Sports Gears",
      "sports": "Cricket",
      "sizes": ["Short Handle", "Long Handle"],
      "thumbnail_url": "https://www.uscricketstore.com/public/uploads/all/K2x2cF58KQ3lklM4uGOlxNFBiHbMY5PeBuGdUFim.jpg",
      "image_gallery": ["cricketbat1_1.jpg", "cricketbat1_2.jpg", "cricketbat1_3.jpg"],
      "rating": 4.7,
      "price": 119.99,
      "description": "Top-quality cricket bat made from premium willow for powerful and precise shots."
    },
    {
      "id": 8,
      "name": "Hockey Stick",
      "category": "Sports Gears",
      "sports": "Hockey",
      "sizes": ["36.5 inches", "37.5 inches"],
      "thumbnail_url": "https://dks.scene7.com/is/image/GolfGalaxy/20STXWHPR101XXXXXFHS_Grey_Carolina_Blue?qlt=70&wid=600&fmt=pjpeg&op_sharpen=1",
      "image_gallery": ["hockeystick1_1.jpg", "hockeystick1_2.jpg", "hockeystick1_3.jpg"],
      "rating": 4.6,
      "price": 79.99,
      "description": "Lightweight and durable hockey stick designed for optimal control and performance."
    },
    {
      "id": 9,
      "name": "Table Tennis Paddle",
      "category": "Sports Gears",
      "sports": "Table Tennis",
      "sizes": ["Standard"],
      "thumbnail_url": "https://target.scene7.com/is/image/Target/GUEST_58864c6e-7071-4996-b2ce-439167a599ea?wid=600&hei=600&qlt=80&fmt=webp",
      "image_gallery": ["tabletennispaddle1_1.jpg", "tabletennispaddle1_2.jpg", "tabletennispaddle1_3.jpg"],
      "rating": 4.8,
      "price": 19.99,
      "description": "High-performance table tennis paddle with ergonomic grip and balanced weight."
    },
    {
      "id": 10,
      "name": "Golf Club Set",
      "category": "Sports Gears",
      "sports": "Golf",
      "sizes": ["Standard"],
      "thumbnail_url": "https://target.scene7.com/is/image/Target/GUEST_89744e06-9825-4e58-9c73-ed275651b222?wid=600&hei=600&qlt=80&fmt=webp",
      "image_gallery": ["golfclubset1_1.jpg", "golfclubset1_2.jpg", "golfclubset1_3.jpg"],
      "rating": 4.7,
      "price": 399.99,
      "description": "Complete set of golf clubs for players of all levels, including drivers, irons, and putter."
    },
    {
      "id": 11,
      "name": "Basketball Jersey",
      "category": "Sportswear",
      "sports": "Basketball",
      "sizes": ["S", "M", "L", "XL"],
      "thumbnail_url": "https://target.scene7.com/is/image/Target/GUEST_d82d1b53-5c1c-4da2-b49f-34c04bb77548?wid=600&hei=600&qlt=80&fmt=webp",
      "image_gallery": ["basketballjersey1_1.jpg", "basketballjersey1_2.jpg", "basketballjersey1_3.jpg"],
      "rating": 4.5,
      "price": 29.99,
      "description": "Breathable and comfortable basketball jersey designed for peak performance."
    },
    {
      "id": 12,
      "name": "Soccer Shorts",
      "category": "Sportswear",
      "sports": "Soccer",
      "sizes": ["S", "M", "L", "XL"],
      "thumbnail_url": "https://target.scene7.com/is/image/Target/GUEST_03dd29a7-bd23-4739-91ac-fce96c29d44d?wid=600&hei=600&qlt=80&fmt=webp",
      "image_gallery": ["soccershorts1_1.jpg", "soccershorts1_2.jpg", "soccershorts1_3.jpg"],
      "rating": 4.6,
      "price": 24.99,
      "description": "Lightweight and durable soccer shorts for ultimate comfort and flexibility on the field."
    },
    {
      "id": 13,
      "name": "Skating Shoes",
      "category": "Sports Gears",
      "sports": "Skating",
      "sizes": ["6", "7.5", "8", "9.5"],
      "thumbnail_url": "https://target.scene7.com/is/image/Target/GUEST_2f8d6600-3667-458b-8156-dd17a2baff12?wid=600&hei=600&qlt=80&fmt=webp",
      "image_gallery": ["runningtights1_1.jpg", "runningtights1_2.jpg", "runningtights1_3.jpg"],
      "rating": 4.7,
      "price": 34.99,
      "description": "The Airwalk adjustable adult inline skates features a molded shell that adjusts sizes with the simple push of a button."
    },
    {
      "id": 14,
      "name": "Cycling Jersey",
      "category": "Sportswear",
      "sports": "Cycling",
      "sizes": ["S", "M", "L", "XL"],
      "thumbnail_url": "https://target.scene7.com/is/image/Target/GUEST_ba340ea9-13ae-44d9-a4fe-4c2ce4bfe054?wid=600&hei=600&qlt=80&fmt=webp",
      "image_gallery": ["cyclingjersey1_1.jpg", "cyclingjersey1_2.jpg", "cyclingjersey1_3.jpg"],
      "rating": 4.8,
      "price": 39.99,
      "description": "Aerodynamic cycling jersey with breathable fabric for enhanced comfort during rides."
    },
    {
      "id": 15,
      "name": "Gym Tank Top",
      "category": "Sportswear",
      "sports": "Gym",
      "sizes": ["S", "M", "L", "XL"],
      "thumbnail_url": "https://target.scene7.com/is/image/Target/GUEST_85429355-8789-4565-81be-1308cf140984?wid=600&hei=600&qlt=80&fmt=webp",
      "image_gallery": ["gymtanktop1_1.jpg", "gymtanktop1_2.jpg", "gymtanktop1_3.jpg"],
      "rating": 4.6,
      "price": 19.99,
      "description": "Lightweight and breathable tank top designed for intense workout sessions."
    },
    {
      "id": 16,
      "name": "Swim Goggles",
      "category": "Sports Gears",
      "sports": "Swimming",
      "sizes": ["Standard"],
      "thumbnail_url": "https://target.scene7.com/is/image/Target/GUEST_f95ebe37-b11f-4563-af26-787e8d18d055?wid=600&hei=600&qlt=80&fmt=webp",
      "image_gallery": ["swimgoggles1_1.jpg", "swimgoggles1_2.jpg", "swimgoggles1_3.jpg"],
      "rating": 4.5,
      "price": 14.99,
      "description": "Anti-fog swim goggles with adjustable strap for a secure and comfortable fit."
    },
    {
      "id": 17,
      "name": "Badminton Racket",
      "category": "Sports Gears",
      "sports": "Badminton",
      "sizes": ["Standard"],
      "thumbnail_url": "https://target.scene7.com/is/image/Target/GUEST_f9cd967f-1df8-40e4-9dd9-23b05ba5e980?wid=600&hei=600&qlt=80&fmt=webp",
      "image_gallery": ["badmintonracket1_1.jpg", "badmintonracket1_2.jpg", "badmintonracket1_3.jpg"],
      "rating": 4.7,
      "price": 34.99,
      "description": "Lightweight and durable badminton racket for powerful and accurate shots."
    },
    {
      "id": 18,
      "name": "Volleyball",
      "category": "Sports Goods",
      "sports": "Volleyball",
      "sizes": ["Standard"],
      "thumbnail_url": "https://target.scene7.com/is/image/Target/GUEST_65eb79a0-c5a5-4051-83ea-3e497265da66?wid=600&hei=600&qlt=80&fmt=webp",
      "image_gallery": ["volleyball1_1.jpg", "volleyball1_2.jpg", "volleyball1_3.jpg"],
      "rating": 4.6,
      "price": 19.99,
      "description": "High-quality volleyball designed for both indoor and outdoor play."
    },
    {
      "id": 19,
      "name": "Gym Bag",
      "category": "Sports Goods",
      "sports": "Gym",
      "sizes": ["Standard"],
      "thumbnail_url": "https://target.scene7.com/is/image/Target/GUEST_6c1d995e-da90-4633-9a53-b2c6337702ee?wid=600&hei=600&qlt=80&fmt=webp",
      "image_gallery": ["gymbag1_1.jpg", "gymbag1_2.jpg", "gymbag1_3.jpg"],
      "rating": 4.7,
      "price": 49.99,
      "description": "Spacious and durable gym bag with multiple compartments for all your gear."
    },
    {
      "id": 20,
      "name": "Football Jersey",
      "category": "Sportswear",
      "sports": "Football",
      "sizes": ["S", "M", "L", "XL"],
      "thumbnail_url": "https://target.scene7.com/is/image/Target/GUEST_1aec09fa-52de-4026-afd7-161723eddc1e?wid=600&hei=600&qlt=80&fmt=webp",
      "image_gallery": ["footballjersey1_1.jpg", "footballjersey1_2.jpg", "footballjersey1_3.jpg"],
      "rating": 4.5,
      "price": 29.99,
      "description": "Comfortable and breathable football jersey designed for optimal performance."
    },
    {
      "id": 21,
      "name": "Tennis Balls",
      "category": "Sports Goods",
      "sports": "Tennis",
      "sizes": ["S", "M", "L", "XL"],
      "thumbnail_url": "https://target.scene7.com/is/image/Target/GUEST_4b670b84-3b2c-4fda-a1ed-eee74d851e5d?wid=600&hei=600&qlt=80&fmt=webp",
      "image_gallery": ["tennisshorts1_1.jpg", "tennisshorts1_2.jpg", "tennisshorts1_3.jpg"],
      "rating": 4.6,
      "price": 24.99,
      "description": "The 3pk Practice Tennis Balls by Franklin Sports are perfect for practice, training or teaching. With a lower PSI than your average tennis ball, this set is a great for understanding ball control."
    },
    {
      "id": 22,
      "name": "Basketball Hoop",
      "category": "Sports Gears",
      "sports": "Basketball",
      "sizes": ["Standard"],
      "thumbnail_url": "https://target.scene7.com/is/image/Target/GUEST_cc1a289c-8407-4fe6-a8fc-02441b181951?wid=600&hei=600&qlt=80&fmt=webp",
      "image_gallery": ["basketballhoop1_1.jpg", "basketballhoop1_2.jpg", "basketballhoop1_3.jpg"],
      "rating": 4.7,
      "price": 149.99,
      "description": "Sturdy and adjustable basketball hoop for both indoor and outdoor use."
    },
    {
      "id": 23,
      "name": "Golf Glove",
      "category": "Sports Gears",
      "sports": "Golf",
      "sizes": ["S", "M", "L"],
      "thumbnail_url": "https://target.scene7.com/is/image/Target/GUEST_5070b0f6-34c4-418a-8d1a-02af739d69f7?wid=600&hei=600&qlt=80&fmt=webp",
      "image_gallery": ["golfglove1_1.jpg", "golfglove1_2.jpg", "golfglove1_3.jpg"],
      "rating": 4.5,
      "price": 19.99,
      "description": "Comfortable and durable golf glove for improved grip and control."
    },
    {
      "id": 24,
      "name": "Swimming Cap",
      "category": "Sports Gears",
      "sports": "Swimming",
      "sizes": ["Standard"],
      "thumbnail_url": "https://target.scene7.com/is/image/Target/GUEST_bce186f6-1200-4746-bf92-9eb29177403d?wid=600&hei=600&qlt=80&fmt=webp",
      "image_gallery": ["swimmingcap1_1.jpg", "swimmingcap1_2.jpg", "swimmingcap1_3.jpg"],
      "rating": 4.4,
      "price": 9.99,
      "description": "Durable and comfortable swimming cap designed to reduce drag in the water."
    },
    {
      "id": 25,
      "name": "Weightlifting Belt",
      "category": "Sports Gears",
      "sports": "Weightlifting",
      "sizes": ["S", "M", "L", "XL"],
      "thumbnail_url": "https://target.scene7.com/is/image/Target/GUEST_a4815636-ff57-460c-8458-973bab215bf6?wid=600&hei=600&qlt=80&fmt=webp",
      "image_gallery": ["weightliftingbelt1_1.jpg", "weightliftingbelt1_2.jpg", "weightliftingbelt1_3.jpg"],
      "rating": 4.6,
      "price": 39.99,
      "description": "Supportive weightlifting belt designed to protect your lower back during heavy lifts."
    },
    {
      "id": 26,
      "name": "Jump Rope",
      "category": "Sports Goods",
      "sports": "Gym",
      "sizes": ["Standard"],
      "thumbnail_url": "https://target.scene7.com/is/image/Target/GUEST_025f943f-eb89-4e58-9a31-da7326c77a28?wid=600&hei=600&qlt=80&fmt=webp",
      "image_gallery": ["jumprope1_1.jpg", "jumprope1_2.jpg", "jumprope1_3.jpg"],
      "rating": 4.7,
      "price": 14.99,
      "description": "Durable jump rope with adjustable length for cardio workouts and training."
    },
    {
      "id": 27,
      "name": "Wilson NFL Football",
      "category": "Sports Goods",
      "sports": "Football",
      "sizes": ["S", "M", "L", "XL"],
      "thumbnail_url": "https://target.scene7.com/is/image/Target/GUEST_4cb37249-648a-482f-b651-76e11c755b84?wid=600&hei=600&qlt=80&fmt=webp",
      "image_gallery": ["basketballshorts1_1.jpg", "basketballshorts1_2.jpg", "basketballshorts1_3.jpg"],
      "rating": 4.6,
      "price": 24.99,
      "description": "The NFL Duke replica football from Wilson matches official NFL sizing for realistic play, and the all-weather design of this professional football lets you enjoy your game in the rain or sun."
    },
    {
      "id": 28,
      "name": "Baseball Cap",
      "category": "Sportswear",
      "sports": "Baseball",
      "sizes": ["Standard"],
      "thumbnail_url": "https://target.scene7.com/is/image/Target/GUEST_59853683-54c2-4baf-885b-3408e7f78ec1?wid=600&hei=600&qlt=80&fmt=webp",
      "image_gallery": ["baseballcap1_1.jpg", "baseballcap1_2.jpg", "baseballcap1_3.jpg"],
      "rating": 4.6,
      "price": 19.99,
      "description": "Classic baseball cap with adjustable strap for a perfect fit."
    }
  ]
  